rcm/__init__.py
rcm/auth.py
rcm/constants.py
rcm/settings.py
rcm/station.py
rcm/station_client.py
rcm/sensors/__init__.py
rcm/sensors/bme680.py
rcm/sensors/sensor.py
rcm/sensors/sgp30.py
rcm/sensors/sht31d.py
rcm/sensors/sys.py
rcm/sensors/tmp_hum_sensor.py
rcm/sensors/tsl2591.py
rcm/util/__init__.py
rcm/util/bool.py
rcm_station_client-0.5.0.dist-info/LICENSE
rcm_station_client-0.5.0.dist-info/METADATA
rcm_station_client-0.5.0.dist-info/WHEEL
rcm_station_client-0.5.0.dist-info/entry_points.txt
rcm_station_client-0.5.0.dist-info/top_level.txt
rcm_station_client-0.5.0.dist-info/RECORD
