Metadata-Version: 2.1
Name: rcm-station-client
Version: 0.5.0
Summary: Collects measurement reports from various sensors and send them to the station-monitoring-service.
Home-page: https://gitlab.com/residential-climate-monitoring/station-client
Author: Pim Hazebroek
Author-email: rcm@pimhazebroek.nl
License: UNKNOWN
Platform: UNKNOWN
Classifier: Programming Language :: Python :: 3
Classifier: License :: OSI Approved :: MIT License
Classifier: Operating System :: OS Independent
Requires-Python: >=3.7
Requires-Dist: requests (==2.27.1)
Requires-Dist: urllib3 (==1.26.9)
Requires-Dist: python-dotenv (==0.20.0)
Requires-Dist: psutil (==5.9.0)
Requires-Dist: adafruit-blinka (==7.2.0)
Requires-Dist: adafruit-circuitpython-busdevice (==5.1.8)
Requires-Dist: adafruit-circuitpython-sht31d (==2.3.10)
Requires-Dist: adafruit-circuitpython-bme680 (==3.4.2)
Requires-Dist: adafruit-circuitpython-tsl2591 (==1.3.2)
Requires-Dist: adafruit-circuitpython-sgp30 (==2.4.0)
Provides-Extra: build
Requires-Dist: setuptools (==50.3.2) ; extra == 'build'
Requires-Dist: pylint ; extra == 'build'
Requires-Dist: bump2version (==1.0.0) ; extra == 'build'
